{
  "ExperimentRef": {
    "ExperimentID": "GEO-J2000-TDB-2431313-2431315-1H",
    "CoreHash": "D0E097AF",
    "CatalogNumber": "AS-000069"
  },
  "DatasetHeader": {
    "Measurement": {
      "Level": "L0",
      "Type": "VEC"
    },
    "DatasetID": "GEO-J2000-TDB-2431313-2431315-1H__EPH-HORIZONS-VEC-L0",
    "TruthMetadata": {
      "CanonicalRequest": "CENTER=500@399\nCOMMAND=899\nCSV_FORMAT=YES\nEPHEM_TYPE=VECTORS\nOBJ_DATA=NO\nOUT_UNITS=AU-D\nREF_PLANE=ECLIPTIC\nREF_SYSTEM=ICRF\nSTART_TIME=JD2431313.299305555\nSTEP_SIZE=1H\nSTOP_TIME=JD2431315.299305555",
      "RequestHash": "A95E5AD2E26006EFA150D5FEC988660D103B633BE21E03C973825E95C77F9DEF",
      "EpochHash": "939065DC46E2B8AC6B5825626177F71B228459FEEED8DD0DE3156B1B2A3CA9A5",
      "Requests": [
        {
          "CanonicalRequest": "CENTER=500@399\nCOMMAND=899\nCSV_FORMAT=YES\nEPHEM_TYPE=VECTORS\nOBJ_DATA=NO\nOUT_UNITS=AU-D\nREF_PLANE=ECLIPTIC\nREF_SYSTEM=ICRF\nSTART_TIME=JD2431313.299305555\nSTEP_SIZE=1H\nSTOP_TIME=JD2431315.299305555",
          "RequestHash": "A95E5AD2E26006EFA150D5FEC988660D103B633BE21E03C973825E95C77F9DEF",
          "HorizonsUrl": "https://ssd.jpl.nasa.gov/api/horizons.api?format=text&COMMAND=899&CENTER=500%40399&START_TIME=JD2431313.299305555&STOP_TIME=JD2431315.299305555&STEP_SIZE=1H&EPHEM_TYPE=VECTORS&CSV_FORMAT=YES&OBJ_DATA=NO&REF_PLANE=ECLIPTIC&REF_SYSTEM=ICRF&OUT_UNITS=AU-D"
        }
      ],
      "TruthProviderUrl": "https://ssd.jpl.nasa.gov/api/horizons.api?format=text&COMMAND=899&CENTER=500%40399&START_TIME=JD2431313.299305555&STOP_TIME=JD2431315.299305555&STEP_SIZE=1H&EPHEM_TYPE=VECTORS&CSV_FORMAT=YES&OBJ_DATA=NO&REF_PLANE=ECLIPTIC&REF_SYSTEM=ICRF&OUT_UNITS=AU-D",
      "GeneratedAtUtc": null
    },
    "FactoryMetadata": {
      "FactoryName": "EphemerisFactory",
      "FactoryVersion": "1.0.0",
      "Source": "JPL Horizons https://ssd.jpl.nasa.gov/horizons/app.html#/",
      "ReferenceEphemeris": "DE440",
      "Mode": "GEO",
      "EphemType": "VECTORS",
      "CorrectionLevel": "L0",
      "TimeScale": "TDB"
    },
    "TruthCitation": {
      "Provider": "NASA - Jet Propulsion Laboratory, California Institute of Technology",
      "Source": "https://ssd.jpl.nasa.gov/horizons/",
      "Citation": "PL Solar System Dynamics Group. JPL Horizons On-Line Ephemeris System. California Institute of Technology. Accessed: 2026-03-23. https://ssd.jpl.nasa.gov/horizons/"
    },
    "Provenance": {
      "ScenarioFactory": "AstronoSphere | MeeusScenarioFactory",
      "TruthFactory": "HorizonsTruthFactory",
      "ValidationTarget": {
        "Software": "AstronoSphere",
        "GitCommit": null,
        "GitBranch": null,
        "GitTag": null
      }
    },
    "EngineCitation": {
      "Author": null,
      "Software": null,
      "Citation": null
    },
    "ValidationFingerprint": null
  },
  "Data": [
    {
      "JD": 2431313.299305554,
      "Position": {"X":-30.92945969996703,"Y":-1.7005001168176179,"Z":0.74388241482114181},
      "Velocity": {"X":-0.01083788885275706,"Y":-0.015987478751218181,"Z":5.769916854840637E-05}
    },
    {
      "JD": 2431313.340972221,
      "Position": {"X":-30.929911090822269,"Y":-1.701166427558976,"Z":0.74388481891195912},
      "Velocity": {"X":-0.01082887119424354,"Y":-0.015995435995281491,"Z":5.7697080477718917E-05}
    },
    {
      "JD": 2431313.382638888,
      "Position": {"X":-30.93036210581662,"Y":-1.701833069747374,"Z":0.74388722290210751},
      "Velocity": {"X":-0.01081984754069743,"Y":-0.01600338821017867,"Z":5.7694339079885677E-05}
    },
    {
      "JD": 2431313.424305554,
      "Position": {"X":-30.930812744701601,"Y":-1.7025000431734121,"Z":0.74388962676469539},
      "Velocity": {"X":-0.010810817954833849,"Y":-0.0160113354034691,"Z":5.7690960193196463E-05}
    },
    {
      "JD": 2431313.465972221,
      "Position": {"X":-30.93126300723133,"Y":-1.703167347628054,"Z":0.74389203047348751},
      "Velocity": {"X":-0.010801782498865641,"Y":-0.016019277584964228,"Z":5.7686959493762779E-05}
    },
    {
      "JD": 2431313.507638888,
      "Position": {"X":-30.93171289316248,"Y":-1.7038349829027011,"Z":0.74389443400289679},
      "Velocity": {"X":-0.01079274123291815,"Y":-0.016027214765433489,"Z":5.768235233271067E-05}
    },
    {
      "JD": 2431313.549305554,
      "Position": {"X":-30.932162402254161,"Y":-1.7045029487891921,"Z":0.74389683732796619},
      "Velocity": {"X":-0.01078369421343572,"Y":-0.016035146955150719,"Z":5.7677153626340317E-05}
    },
    {
      "JD": 2431313.590972221,
      "Position": {"X":-30.932611534267739,"Y":-1.7051712450797629,"Z":0.74389924042435063},
      "Velocity": {"X":-0.010774641491706699,"Y":-0.01604307416236618,"Z":5.7671377819493103E-05}
    },
    {
      "JD": 2431313.632638888,
      "Position": {"X":-30.93306028896658,"Y":-1.7058398715669221,"Z":0.74390164326829733},
      "Velocity": {"X":-0.010765583112632151,"Y":-0.016050996391793072,"Z":5.7665038940048063E-05}
    },
    {
      "JD": 2431313.674305554,
      "Position": {"X":-30.933508666115738,"Y":-1.7065088280432761,"Z":0.74390404583663305},
      "Velocity": {"X":-0.0107565191138534,"Y":-0.01605891364319742,"Z":5.7658150758619492E-05}
    },
    {
      "JD": 2431313.715972221,
      "Position": {"X":-30.933956665481759,"Y":-1.707178114301297,"Z":0.74390644810675621},
      "Velocity": {"X":-0.010747449525338831,"Y":-0.016066825910177419,"Z":5.7650727062421281E-05}
    },
    {
      "JD": 2431313.757638888,
      "Position": {"X":-30.934404286832201,"Y":-1.707847730133045,"Z":0.7439088500566472},
      "Velocity": {"X":-0.01073837436950714,"Y":-0.016074733179211442,"Z":5.7642782045660667E-05}
    },
    {
      "JD": 2431313.799305554,
      "Position": {"X":-30.93485152993545,"Y":-1.708517675329857,"Z":0.74391125166489513},
      "Velocity": {"X":-0.010729293661936021,"Y":-0.016082635429044079,"Z":5.7634330810871153E-05}
    },
    {
      "JD": 2431313.840972221,
      "Position": {"X":-30.935298394560402,"Y":-1.709187949682019,"Z":0.74391365291074707},
      "Velocity": {"X":-0.01072020741266963,"Y":-0.016090532630466,"Z":5.7625389966232623E-05}
    },
    {
      "JD": 2431313.882638888,
      "Position": {"X":-30.935744880476289,"Y":-1.709858552978436,"Z":0.74391605377418513},
      "Velocity": {"X":-0.010711115628096041,"Y":-0.01609842474652649,"Z":5.7615978293176072E-05}
    },
    {
      "JD": 2431313.924305554,
      "Position": {"X":-30.936190987452591,"Y":-1.710529485006324,"Z":0.74391845423603142},
      "Velocity": {"X":-0.010702018313317629,"Y":-0.01610631173319722,"Z":5.7606117446395373E-05}
    },
    {
      "JD": 2431313.965972221,
      "Position": {"X":-30.936636715259009,"Y":-1.7112007455509359,"Z":0.74392085427808197},
      "Velocity": {"X":-0.010692915474881749,"Y":-0.016114193540481919,"Z":5.7595832634870163E-05}
    },
    {
      "JD": 2431314.007638888,
      "Position": {"X":-30.937082063665599,"Y":-1.7118723343953399,"Z":0.74392325388326797},
      "Velocity": {"X":-0.010683807123677679,"Y":-0.016122070113939461,"Z":5.7585153217528019E-05}
    },
    {
      "JD": 2431314.049305554,
      "Position": {"X":-30.937527032443001,"Y":-1.71254425132028,"Z":0.74392565303583857},
      "Velocity": {"X":-0.0106746932777374,"Y":-0.01612994139655706,"Z":5.7574113130837558E-05}
    },
    {
      "JD": 2431314.090972221,
      "Position": {"X":-30.937971621362809,"Y":-1.7132164961041041,"Z":0.74392805172155485},
      "Velocity": {"X":-0.01066557396460269,"Y":-0.016137807330876271,"Z":5.7562751047910918E-05}
    },
    {
      "JD": 2431314.132638888,
      "Position": {"X":-30.938415830197979,"Y":-1.7138890685227961,"Z":0.74393044992788504},
      "Velocity": {"X":-0.01065644922283974,"Y":-0.01614566786123672,"Z":5.7551110149479908E-05}
    },
    {
      "JD": 2431314.174305554,
      "Position": {"X":-30.938859658723331,"Y":-1.7145619683500981,"Z":0.74393284764417866},
      "Velocity": {"X":-0.01064731910219455,"Y":-0.016153522935961749,"Z":5.7539237366685368E-05}
    },
    {
      "JD": 2431314.215972221,
      "Position": {"X":-30.93930310671594,"Y":-1.7152351953577141,"Z":0.7439352448617953},
      "Velocity": {"X":-0.01063818366178732,"Y":-0.01616137250926529,"Z":5.7527181933604189E-05}
    },
    {
      "JD": 2431314.257638888,
      "Position": {"X":-30.939746173955491,"Y":-1.71590874931559,"Z":0.74393764157415487},
      "Velocity": {"X":-0.010629042965643281,"Y":-0.01616921654261191,"Z":5.7514993064114717E-05}
    },
    {
      "JD": 2431314.299305554,
      "Position": {"X":-30.940188860224278,"Y":-1.716582629992224,"Z":0.74394003777667028},
      "Velocity": {"X":-0.01061989707474946,"Y":-0.016177055005209929,"Z":5.7502716543035863E-05}
    },
    {
      "JD": 2431314.340972221,
      "Position": {"X":-30.940631165306879,"Y":-1.7172568371549859,"Z":0.74394243346651179},
      "Velocity": {"X":-0.01061074603471243,"Y":-0.016184887873263401,"Z":5.749038999529024E-05}
    },
    {
      "JD": 2431314.382638888,
      "Position": {"X":-30.941073088989182,"Y":-1.7179313705703601,"Z":0.7439448286421404},
      "Velocity": {"X":-0.01060158985797123,"Y":-0.016192715127550088,"Z":5.7478036569368628E-05}
    },
    {
      "JD": 2431314.424305554,
      "Position": {"X":-30.94151463105645,"Y":-1.718606230004049,"Z":0.74394722330254104},
      "Velocity": {"X":-0.01059242849939228,"Y":-0.01620053674883095,"Z":5.746565674241042E-05}
    },
    {
      "JD": 2431314.465972221,
      "Position": {"X":-30.94195579129034,"Y":-1.719281415220832,"Z":0.74394961744607069},
      "Velocity": {"X":-0.010583261823938711,"Y":-0.016208352710531559,"Z":5.7453217923949171E-05}
    },
    {
      "JD": 2431314.507638888,
      "Position": {"X":-30.942396569464581,"Y":-1.7199569259842049,"Z":0.74395201106887099},
      "Velocity": {"X":-0.0105740896404497,"Y":-0.016216163004073469,"Z":5.7440658833708793E-05}
    },
    {
      "JD": 2431314.549305554,
      "Position": {"X":-30.9428369653589,"Y":-1.720632762054769,"Z":0.74395440417105996},
      "Velocity": {"X":-0.01056491245357696,"Y":-0.01622396733317481,"Z":5.7428301300145572E-05}
    },
    {
      "JD": 2431314.590972221,
      "Position": {"X":-30.943276978766502,"Y":-1.7213089231766441,"Z":0.74395679676463977},
      "Velocity": {"X":-0.01055573028249761,"Y":-0.016231765513737041,"Z":5.7416232798132118E-05}
    },
    {
      "JD": 2431314.632638888,
      "Position": {"X":-30.943716609480099,"Y":-1.7219854090985229,"Z":0.74395918886033485},
      "Velocity": {"X":-0.01054654314168561,"Y":-0.01623955775850908,"Z":5.7404396344504093E-05}
    },
    {
      "JD": 2431314.674305554,
      "Position": {"X":-30.94415585729255,"Y":-1.7226622195755379,"Z":0.74396158046720007},
      "Velocity": {"X":-0.010537351026130329,"Y":-0.016247344170131701,"Z":5.7392766874528928E-05}
    },
    {
      "JD": 2431314.715972221,
      "Position": {"X":-30.944594721996271,"Y":-1.723339354365421,"Z":0.74396397159373284},
      "Velocity": {"X":-0.01052815391769903,"Y":-0.016255124775996301,"Z":5.7381341287369451E-05}
    },
    {
      "JD": 2431314.757638888,
      "Position": {"X":-30.94503320338265,"Y":-1.7240168132259519,"Z":0.743966362248625},
      "Velocity": {"X":-0.01051895178998968,"Y":-0.0162628995547663,"Z":5.7370130867961827E-05}
    },
    {
      "JD": 2431314.799305554,
      "Position": {"X":-30.945471301241948,"Y":-1.7246945959133591,"Z":0.74396875244123695},
      "Velocity": {"X":-0.010509744611940319,"Y":-0.016270668455988849,"Z":5.7359155681159422E-05}
    },
    {
      "JD": 2431314.840972221,
      "Position": {"X":-30.945909015363039,"Y":-1.72537270218141,"Z":0.74397114218187654},
      "Velocity": {"X":-0.010500532350429489,"Y":-0.01627843141406906,"Z":5.7348440576861568E-05}
    },
    {
      "JD": 2431314.882638888,
      "Position": {"X":-30.946346345533421,"Y":-1.7260511317809979,"Z":0.7439735314819379},
      "Velocity": {"X":-0.010491314972072591,"Y":-0.01628618835773115,"Z":5.7338012485857148E-05}
    },
    {
      "JD": 2431314.924305554,
      "Position": {"X":-30.946783291539191,"Y":-1.7267298844600321,"Z":0.74397592035394944},
      "Velocity": {"X":-0.010482092444391021,"Y":-0.016293939215951962,"Z":5.7327898724839268E-05}
    },
    {
      "JD": 2431314.965972221,
      "Position": {"X":-30.947219853165169,"Y":-1.7274089599635341,"Z":0.74397830881156968},
      "Velocity": {"X":-0.010472864736504999,"Y":-0.016301683921220521,"Z":5.7318126065590708E-05}
    },
    {
      "JD": 2431315.007638888,
      "Position": {"X":-30.947656030194889,"Y":-1.728088358033804,"Z":0.74398069686955193},
      "Velocity": {"X":-0.010463631819476651,"Y":-0.016309422410854781,"Z":5.7308720357718877E-05}
    },
    {
      "JD": 2431315.049305554,
      "Position": {"X":-30.948091822410731,"Y":-1.728768078410637,"Z":0.74398308454370909},
      "Velocity": {"X":-0.01045439366640777,"Y":-0.016317154626991289,"Z":5.7299706526613237E-05}
    },
    {
      "JD": 2431315.090972221,
      "Position": {"X":-30.948527229594021,"Y":-1.7294481208315049,"Z":0.74398547185087527},
      "Velocity": {"X":-0.010445150252376009,"Y":-0.016324880515757059,"Z":5.7291108798245482E-05}
    },
    {
      "JD": 2431315.132638888,
      "Position": {"X":-30.948962251525039,"Y":-1.7301284850316929,"Z":0.74398785880888607},
      "Velocity": {"X":-0.010435901554275019,"Y":-0.016332600026033969,"Z":5.7282951030420293E-05}
    },
    {
      "JD": 2431315.174305554,
      "Position": {"X":-30.949396887983191,"Y":-1.730809170744394,"Z":0.74399024543656911},
      "Velocity": {"X":-0.01042664755060675,"Y":-0.016340313108135669,"Z":5.7275257055678822E-05}
    },
    {
      "JD": 2431315.215972221,
      "Position": {"X":-30.949831138746969,"Y":-1.7314901777007381,"Z":0.74399263175374997},
      "Velocity": {"X":-0.01041738822126002,"Y":-0.016348019712634668,"Z":5.7268050964740018E-05}
    },
    {
      "JD": 2431315.257638888,
      "Position": {"X":-30.950265003594069,"Y":-1.7321715056297859,"Z":0.7439950177812662},
      "Velocity": {"X":-0.010408123547295671,"Y":-0.016355719789502711,"Z":5.7261357280544898E-05}
    },
    {
      "JD": 2431315.299305554,
      "Position": {"X":-30.950698482301419,"Y":-1.7328531542584931,"Z":0.74399740354098709},
      "Velocity": {"X":-0.010398853510748081,"Y":-0.016363413287661829,"Z":5.7255200992382073E-05}
    }
  ]
}