{
  "SchemaVersion": "1.0",
  "ExperimentID": "HELIO-J2000-TDB-2597641-2634151-30D",
  "CatalogNumber": "AS-000138",
  "CoreHash": "C2A33CFF",
  "Core": {
    "Time": {
      "StartJD": 2597641.5,
      "StopJD": 2634151.5,
      "Step": "30D",
      "TimeScale": "TDB"
    },
    "Observer": {
      "Type": "Heliocentric",
      "Body": "Sun"
    },
    "ObservedObject": {
      "BodyClass": "Planet",
      "Targets": [
        "Venus"
      ]
    },
    "Frame": {
      "Type": "HelioEcliptic",
      "Epoch": "J2000"
    }
  },
  "Event": {
    "Category": "MeshValidation",
    "Qualifier": "CoreZone 2400-2500, Step30D",
    "Description": "2597641.500000"
  },
  "Metadata": {
    "Author": "Scenario Merger",
    "Priority": 1,
    "Status": {
      "Maturity": "Released",
      "Visibility": "Private"
    }
  },
  "Notes": "Scenario Merger: Generated automatically from 144 existing scenarios."
}