{
  "SchemaVersion": "1.0",
  "ExperimentID": "HELIO-J2000-TDB-2460835-2460837-1H",
  "CatalogNumber": "AS-000145",
  "CoreHash": "TO_BE_REPLACED",
  "Core": {
    "Time": {
      "StartJD": 2460835.7125,
      "StopJD": 2460837.7125,
      "Step": "1H",
      "TimeScale": "TDB"
    },
    "Observer": {
      "Type": "Heliocentric",
      "Body": "Sun"
    },
    "ObservedObject": {
      "BodyClass": "Planet",
      "Targets": [
        "Mars"
      ]
    },
    "Frame": {
      "Type": "HelioEcliptic",
      "Epoch": "J2000"
    }
  },
  "Event": {
    "Category": "Quadrant Crossing",
    "Qualifier": "L12 Crossing: Y Coordinate: + to -",
    "Description": "2460836.7125"
  },
  "Metadata": {
    "Author": "Scenario Merger",
    "Priority": 1,
    "Status": {
      "Maturity": "Released",
      "Visibility": "Private"
    }
  },
  "Notes": "Generated manually: replaces false Dataset #34 from initial data base (dublette with #35 - Jupiter)."
}