{
  "ScenarioRef": {
    "ScenarioID": "GEO-TDB-2371542.083-2371544.083-1H",
    "CoreHash": "264C136C",
    "CatalogNumber": "AS-000009"
  },
"DatasetHeader": {
  "Measurement": {
    "Level": "L0",
    "Type": "VEC"
  },

    "DatasetID": "GEO-TDB-2371542.083-2371544.083-1H--EPH-HORIZONS-DE440-L0-VEC",

    "TruthMetadata": {
      "CanonicalRequest": "CENTER=500@399\nCOMMAND=799\nCSV_FORMAT=YES\nEPHEM_TYPE=VECTORS\nOBJ_DATA=NO\nOUT_UNITS=AU-D\nREF_PLANE=ECLIPTIC\nREF_SYSTEM=ICRF\nSTART_TIME=JD2371542.083\nSTEP_SIZE=1H\nSTOP_TIME=JD2371544.083",
      "RequestHash": "088C1E2E748453A52436238A886CE13F6267276BBD2D67D660920124EA2C71FB",
      "EpochHash": "2806F08629D4E8EA2B549F5FC6F8AA2AE35A36D5D0F42CB2699E614A02826A03",
      "Requests": [{"CanonicalRequest": "CENTER=500@399\nCOMMAND=799\nCSV_FORMAT=YES\nEPHEM_TYPE=VECTORS\nOBJ_DATA=NO\nOUT_UNITS=AU-D\nREF_PLANE=ECLIPTIC\nREF_SYSTEM=ICRF\nSTART_TIME=JD2371542.083\nSTEP_SIZE=1H\nSTOP_TIME=JD2371544.083", "RequestHash": "088C1E2E748453A52436238A886CE13F6267276BBD2D67D660920124EA2C71FB", "HorizonsUrl": "https://ssd.jpl.nasa.gov/api/horizons.api?format=text&input=CENTER%3D500%40399%0ACOMMAND%3D799%0ACSV_FORMAT%3DYES%0AEPHEM_TYPE%3DVECTORS%0AOBJ_DATA%3DNO%0AOUT_UNITS%3DAU-D%0AREF_PLANE%3DECLIPTIC%0AREF_SYSTEM%3DICRF%0ASTART_TIME%3DJD2371542.083%0ASTEP_SIZE%3D1H%0ASTOP_TIME%3DJD2371544.083"}],
      "TruthProviderUrl": "https://ssd.jpl.nasa.gov/api/horizons.api?format=text&input=CENTER%3D500%40399%0ACOMMAND%3D799%0ACSV_FORMAT%3DYES%0AEPHEM_TYPE%3DVECTORS%0AOBJ_DATA%3DNO%0AOUT_UNITS%3DAU-D%0AREF_PLANE%3DECLIPTIC%0AREF_SYSTEM%3DICRF%0ASTART_TIME%3DJD2371542.083%0ASTEP_SIZE%3D1H%0ASTOP_TIME%3DJD2371544.083",
      "GeneratedAtUtc": null
    },

    "FactoryMetadata": {
      "FactoryName": "EphemerisFactory",
      "FactoryVersion": "1.0.0",
      "Source": "JPL Horizons https://ssd.jpl.nasa.gov/horizons/app.html#/",
      "ReferenceEphemeris": "DE440",
      "Mode": "GEO",
      "EphemType": "VECTORS",
      "CorrectionLevel": "L0",
      "TimeScale": "TDB"
    },

    "TruthCitation": {
      "Provider": "NASA - Jet Propulsion Laboratory, California Institute of Technology",
      "Source": "https://ssd.jpl.nasa.gov/horizons/",
      "Citation": "PL Solar System Dynamics Group. JPL Horizons On-Line Ephemeris System. California Institute of Technology. Accessed: 2026-03-23. https://ssd.jpl.nasa.gov/horizons/"
    },

    "Provenance": {
      "ScenarioFactory": "AstronoSphere | MeeusScenarioFactory",
      "TruthFactory": "HorizonsTruthFactory",
      "ValidationTarget": {
        "Software": "AstronoSphere",
        "GitCommit": null,
        "GitBranch": null,
        "GitTag": null
      }
    },

    "EngineCitation": {
      "Author": null,
      "Software": null,
      "Citation": null
    },

    "ValidationFingerprint": null
  ,
"Data": [
  {
    "JD": 2371542.083,
    "Position": { "X": 0.14677732, "Y": 18.01230549, "Z": 0.06908762 },
    "Velocity": { "X": 0.01351841, "Y": -0.00057326, "Z": 0.00005133 }
  },
  {
    "JD": 2371542.12466667,
    "Position": { "X": 0.1473406, "Y": 18.01228187, "Z": 0.06908975 },
    "Velocity": { "X": 0.01351882, "Y": -0.00056059, "Z": 0.00005134 }
  },
  {
    "JD": 2371542.16633333,
    "Position": { "X": 0.14790389, "Y": 18.01225877, "Z": 0.06909189 },
    "Velocity": { "X": 0.01351922, "Y": -0.00054792, "Z": 0.00005134 }
  },
  {
    "JD": 2371542.208,
    "Position": { "X": 0.1484672, "Y": 18.0122362, "Z": 0.06909403 },
    "Velocity": { "X": 0.01351961, "Y": -0.00053525, "Z": 0.00005134 }
  },
  {
    "JD": 2371542.24966667,
    "Position": { "X": 0.14903053, "Y": 18.01221417, "Z": 0.06909617 },
    "Velocity": { "X": 0.01352, "Y": -0.00052258, "Z": 0.00005135 }
  },
  {
    "JD": 2371542.29133333,
    "Position": { "X": 0.14959387, "Y": 18.01219266, "Z": 0.06909831 },
    "Velocity": { "X": 0.01352037, "Y": -0.00050991, "Z": 0.00005135 }
  },
  {
    "JD": 2371542.333,
    "Position": { "X": 0.15015722, "Y": 18.01217167, "Z": 0.06910045 },
    "Velocity": { "X": 0.01352074, "Y": -0.00049723, "Z": 0.00005135 }
  },
  {
    "JD": 2371542.37466667,
    "Position": { "X": 0.15072059, "Y": 18.01215122, "Z": 0.06910259 },
    "Velocity": { "X": 0.0135211, "Y": -0.00048456, "Z": 0.00005136 }
  },
  {
    "JD": 2371542.41633333,
    "Position": { "X": 0.15128398, "Y": 18.01213129, "Z": 0.06910473 },
    "Velocity": { "X": 0.01352145, "Y": -0.00047188, "Z": 0.00005136 }
  },
  {
    "JD": 2371542.458,
    "Position": { "X": 0.15184738, "Y": 18.0121119, "Z": 0.06910687 },
    "Velocity": { "X": 0.01352179, "Y": -0.0004592, "Z": 0.00005137 }
  },
  {
    "JD": 2371542.49966667,
    "Position": { "X": 0.1524108, "Y": 18.01209303, "Z": 0.06910901 },
    "Velocity": { "X": 0.01352212, "Y": -0.00044653, "Z": 0.00005137 }
  },
  {
    "JD": 2371542.54133333,
    "Position": { "X": 0.15297423, "Y": 18.01207469, "Z": 0.06911115 },
    "Velocity": { "X": 0.01352244, "Y": -0.00043385, "Z": 0.00005137 }
  },
  {
    "JD": 2371542.583,
    "Position": { "X": 0.15353767, "Y": 18.01205687, "Z": 0.06911329 },
    "Velocity": { "X": 0.01352276, "Y": -0.00042117, "Z": 0.00005138 }
  },
  {
    "JD": 2371542.62466667,
    "Position": { "X": 0.15410112, "Y": 18.01203959, "Z": 0.06911543 },
    "Velocity": { "X": 0.01352306, "Y": -0.00040849, "Z": 0.00005138 }
  },
  {
    "JD": 2371542.66633333,
    "Position": { "X": 0.15466459, "Y": 18.01202283, "Z": 0.06911757 },
    "Velocity": { "X": 0.01352336, "Y": -0.00039581, "Z": 0.00005139 }
  },
  {
    "JD": 2371542.708,
    "Position": { "X": 0.15522807, "Y": 18.01200661, "Z": 0.06911972 },
    "Velocity": { "X": 0.01352365, "Y": -0.00038313, "Z": 0.00005139 }
  },
  {
    "JD": 2371542.74966667,
    "Position": { "X": 0.15579156, "Y": 18.01199091, "Z": 0.06912186 },
    "Velocity": { "X": 0.01352393, "Y": -0.00037044, "Z": 0.0000514 }
  },
  {
    "JD": 2371542.79133333,
    "Position": { "X": 0.15635506, "Y": 18.01197573, "Z": 0.069124 },
    "Velocity": { "X": 0.0135242, "Y": -0.00035776, "Z": 0.0000514 }
  },
  {
    "JD": 2371542.833,
    "Position": { "X": 0.15691858, "Y": 18.01196109, "Z": 0.06912614 },
    "Velocity": { "X": 0.01352447, "Y": -0.00034508, "Z": 0.0000514 }
  },
  {
    "JD": 2371542.87466667,
    "Position": { "X": 0.1574821, "Y": 18.01194698, "Z": 0.06912828 },
    "Velocity": { "X": 0.01352472, "Y": -0.00033239, "Z": 0.0000514 }
  },
  {
    "JD": 2371542.91633333,
    "Position": { "X": 0.15804564, "Y": 18.01193339, "Z": 0.06913042 },
    "Velocity": { "X": 0.01352496, "Y": -0.00031971, "Z": 0.00005141 }
  },
  {
    "JD": 2371542.958,
    "Position": { "X": 0.15860918, "Y": 18.01192034, "Z": 0.06913257 },
    "Velocity": { "X": 0.0135252, "Y": -0.00030702, "Z": 0.00005141 }
  },
  {
    "JD": 2371542.99966667,
    "Position": { "X": 0.15917274, "Y": 18.01190781, "Z": 0.06913471 },
    "Velocity": { "X": 0.01352543, "Y": -0.00029433, "Z": 0.00005141 }
  },
  {
    "JD": 2371543.04133333,
    "Position": { "X": 0.1597363, "Y": 18.01189581, "Z": 0.06913685 },
    "Velocity": { "X": 0.01352564, "Y": -0.00028164, "Z": 0.00005141 }
  },
  {
    "JD": 2371543.083,
    "Position": { "X": 0.16029987, "Y": 18.01188434, "Z": 0.06913899 },
    "Velocity": { "X": 0.01352585, "Y": -0.00026895, "Z": 0.00005141 }
  },
  {
    "JD": 2371543.12466667,
    "Position": { "X": 0.16086345, "Y": 18.0118734, "Z": 0.06914113 },
    "Velocity": { "X": 0.01352605, "Y": -0.00025626, "Z": 0.00005141 }
  },
  {
    "JD": 2371543.16633333,
    "Position": { "X": 0.16142704, "Y": 18.01186298, "Z": 0.06914328 },
    "Velocity": { "X": 0.01352624, "Y": -0.00024357, "Z": 0.00005141 }
  },
  {
    "JD": 2371543.208,
    "Position": { "X": 0.16199064, "Y": 18.0118531, "Z": 0.06914542 },
    "Velocity": { "X": 0.01352642, "Y": -0.00023088, "Z": 0.00005141 }
  },
  {
    "JD": 2371543.24966667,
    "Position": { "X": 0.16255425, "Y": 18.01184374, "Z": 0.06914756 },
    "Velocity": { "X": 0.01352659, "Y": -0.00021819, "Z": 0.00005141 }
  },
  {
    "JD": 2371543.29133333,
    "Position": { "X": 0.16311786, "Y": 18.01183492, "Z": 0.0691497 },
    "Velocity": { "X": 0.01352675, "Y": -0.00020549, "Z": 0.00005141 }
  },
  {
    "JD": 2371543.333,
    "Position": { "X": 0.16368147, "Y": 18.01182662, "Z": 0.06915184 },
    "Velocity": { "X": 0.0135269, "Y": -0.0001928, "Z": 0.00005141 }
  },
  {
    "JD": 2371543.37466667,
    "Position": { "X": 0.1642451, "Y": 18.01181885, "Z": 0.06915399 },
    "Velocity": { "X": 0.01352704, "Y": -0.0001801, "Z": 0.0000514 }
  },
  {
    "JD": 2371543.41633333,
    "Position": { "X": 0.16480873, "Y": 18.01181161, "Z": 0.06915613 },
    "Velocity": { "X": 0.01352717, "Y": -0.00016741, "Z": 0.0000514 }
  },
  {
    "JD": 2371543.458,
    "Position": { "X": 0.16537236, "Y": 18.0118049, "Z": 0.06915827 },
    "Velocity": { "X": 0.0135273, "Y": -0.00015471, "Z": 0.0000514 }
  },
  {
    "JD": 2371543.49966667,
    "Position": { "X": 0.165936, "Y": 18.01179872, "Z": 0.06916041 },
    "Velocity": { "X": 0.01352741, "Y": -0.00014201, "Z": 0.0000514 }
  },
  {
    "JD": 2371543.54133333,
    "Position": { "X": 0.16649965, "Y": 18.01179306, "Z": 0.06916255 },
    "Velocity": { "X": 0.01352751, "Y": -0.00012931, "Z": 0.0000514 }
  },
  {
    "JD": 2371543.583,
    "Position": { "X": 0.16706329, "Y": 18.01178794, "Z": 0.06916469 },
    "Velocity": { "X": 0.0135276, "Y": -0.00011661, "Z": 0.00005139 }
  },
  {
    "JD": 2371543.62466667,
    "Position": { "X": 0.16762695, "Y": 18.01178335, "Z": 0.06916684 },
    "Velocity": { "X": 0.01352769, "Y": -0.00010391, "Z": 0.00005139 }
  },
  {
    "JD": 2371543.66633333,
    "Position": { "X": 0.1681906, "Y": 18.01177928, "Z": 0.06916898 },
    "Velocity": { "X": 0.01352776, "Y": -0.00009121, "Z": 0.00005139 }
  },
  {
    "JD": 2371543.708,
    "Position": { "X": 0.16875426, "Y": 18.01177575, "Z": 0.06917112 },
    "Velocity": { "X": 0.01352782, "Y": -0.00007851, "Z": 0.00005139 }
  },
  {
    "JD": 2371543.74966667,
    "Position": { "X": 0.16931792, "Y": 18.01177274, "Z": 0.06917326 },
    "Velocity": { "X": 0.01352788, "Y": -0.00006581, "Z": 0.00005139 }
  },
  {
    "JD": 2371543.79133333,
    "Position": { "X": 0.16988158, "Y": 18.01177026, "Z": 0.0691754 },
    "Velocity": { "X": 0.01352792, "Y": -0.0000531, "Z": 0.00005139 }
  },
  {
    "JD": 2371543.833,
    "Position": { "X": 0.17044525, "Y": 18.01176831, "Z": 0.06917754 },
    "Velocity": { "X": 0.01352796, "Y": -0.0000404, "Z": 0.00005139 }
  },
  {
    "JD": 2371543.87466667,
    "Position": { "X": 0.17100891, "Y": 18.0117669, "Z": 0.06917968 },
    "Velocity": { "X": 0.01352798, "Y": -0.00002769, "Z": 0.00005138 }
  },
  {
    "JD": 2371543.91633333,
    "Position": { "X": 0.17157258, "Y": 18.01176601, "Z": 0.06918182 },
    "Velocity": { "X": 0.013528, "Y": -0.00001498, "Z": 0.00005138 }
  },
  {
    "JD": 2371543.958,
    "Position": { "X": 0.17213625, "Y": 18.01176565, "Z": 0.06918396 },
    "Velocity": { "X": 0.01352801, "Y": -0.00000227, "Z": 0.00005138 }
  },
  {
    "JD": 2371543.99966667,
    "Position": { "X": 0.17269991, "Y": 18.01176582, "Z": 0.06918611 },
    "Velocity": { "X": 0.013528, "Y": 0.00001043, "Z": 0.00005139 }
  },
  {
    "JD": 2371544.04133333,
    "Position": { "X": 0.17326358, "Y": 18.01176652, "Z": 0.06918825 },
    "Velocity": { "X": 0.01352799, "Y": 0.00002314, "Z": 0.00005139 }
  },
  {
    "JD": 2371544.083,
    "Position": { "X": 0.17382724, "Y": 18.01176775, "Z": 0.06919039 },
    "Velocity": { "X": 0.01352797, "Y": 0.00003585, "Z": 0.00005139 }
  }
]

}